[
  {
    "full_name": "neovim/neovim",
    "stargazers_count": 82327,
    "open_issues_count": 1788,
    "forks_count": 5622
  },
  {
    "full_name": "Shopify/hydrogen",
    "stargazers_count": 1382,
    "open_issues_count": 124,
    "forks_count": 264
  },
  {
    "full_name": "sanity-io/hydrogen-sanity-demo",
    "stargazers_count": 332,
    "open_issues_count": 15,
    "forks_count": 86
  },
  {
    "full_name": "sanity-io/hydrogen-sanity-demo",
    "stargazers_count": 332,
    "open_issues_count": 15,
    "forks_count": 86
  },
  {
    "full_name": "nvimdev/dashboard-nvim",
    "stargazers_count": 2340,
    "open_issues_count": 66,
    "forks_count": 190
  },
  {
    "full_name": "open-sauced/open-sauced",
    "stargazers_count": 935,
    "open_issues_count": 0,
    "forks_count": 993
  }
]