[
  {
    "full_name": "neovim/neovim",
    "stargazers_count": 77118,
    "open_issues_count": 1723,
    "forks_count": 5324
  },
  {
    "full_name": "Shopify/hydrogen",
    "stargazers_count": 1188,
    "open_issues_count": 146,
    "forks_count": 241
  },
  {
    "full_name": "sanity-io/hydrogen-sanity-demo",
    "stargazers_count": 327,
    "open_issues_count": 16,
    "forks_count": 84
  },
  {
    "full_name": "sanity-io/hydrogen-sanity-demo",
    "stargazers_count": 327,
    "open_issues_count": 16,
    "forks_count": 84
  },
  {
    "full_name": "nvimdev/dashboard-nvim",
    "stargazers_count": 2081,
    "open_issues_count": 50,
    "forks_count": 167
  },
  {
    "full_name": "open-sauced/open-sauced",
    "stargazers_count": 920,
    "open_issues_count": 0,
    "forks_count": 892
  }
]