[
  {
    "full_name": "neovim/neovim",
    "stargazers_count": 60229,
    "open_issues_count": 1631,
    "forks_count": 4186
  },
  {
    "full_name": "Shopify/hydrogen",
    "stargazers_count": 3723,
    "open_issues_count": 191,
    "forks_count": 310
  },
  {
    "full_name": "sanity-io/hydrogen-sanity-demo",
    "stargazers_count": 168,
    "open_issues_count": 3,
    "forks_count": 45
  },
  {
    "full_name": "sanity-io/hydrogen-sanity-demo",
    "stargazers_count": 168,
    "open_issues_count": 3,
    "forks_count": 45
  },
  {
    "full_name": "glepnir/dashboard-nvim",
    "stargazers_count": 1239,
    "open_issues_count": 9,
    "forks_count": 98
  },
  {
    "full_name": "open-sauced/open-sauced",
    "stargazers_count": 817,
    "open_issues_count": 10,
    "forks_count": 458
  }
]