[
  {
    "full_name": "neovim/neovim",
    "stargazers_count": 89035,
    "open_issues_count": 1919,
    "forks_count": 6050
  },
  {
    "full_name": "Shopify/hydrogen",
    "stargazers_count": 1612,
    "open_issues_count": 139,
    "forks_count": 313
  },
  {
    "full_name": "sanity-io/hydrogen-sanity-demo",
    "stargazers_count": 335,
    "open_issues_count": 15,
    "forks_count": 88
  },
  {
    "full_name": "sanity-io/hydrogen-sanity-demo",
    "stargazers_count": 335,
    "open_issues_count": 15,
    "forks_count": 88
  },
  {
    "full_name": "nvimdev/dashboard-nvim",
    "stargazers_count": 2579,
    "open_issues_count": 70,
    "forks_count": 195
  },
  {
    "full_name": "open-sauced/open-sauced",
    "stargazers_count": 948,
    "open_issues_count": 0,
    "forks_count": 1104
  }
]