[
  {
    "full_name": "neovim/neovim",
    "stargazers_count": 81601,
    "open_issues_count": 1768,
    "forks_count": 5584
  },
  {
    "full_name": "Shopify/hydrogen",
    "stargazers_count": 1344,
    "open_issues_count": 113,
    "forks_count": 261
  },
  {
    "full_name": "sanity-io/hydrogen-sanity-demo",
    "stargazers_count": 332,
    "open_issues_count": 15,
    "forks_count": 86
  },
  {
    "full_name": "sanity-io/hydrogen-sanity-demo",
    "stargazers_count": 332,
    "open_issues_count": 15,
    "forks_count": 86
  },
  {
    "full_name": "nvimdev/dashboard-nvim",
    "stargazers_count": 2301,
    "open_issues_count": 62,
    "forks_count": 188
  },
  {
    "full_name": "open-sauced/open-sauced",
    "stargazers_count": 934,
    "open_issues_count": 0,
    "forks_count": 964
  }
]